setup.py
envmgr/__init__.py
envmgr/command.py
envmgr/parser.py
envmgr.egg-info/PKG-INFO
envmgr.egg-info/SOURCES.txt
envmgr.egg-info/dependency_links.txt
envmgr.egg-info/entry_points.txt
envmgr.egg-info/top_level.txt
test/__init__.py
test/test_parser.py