Metadata-Version: 1.0
Name: envmgr
Version: 0.0.1
Summary: envmgr: control the environment of spawned programs with config files
Home-page: https://github.com/nickstenning/envmgr
Author: Nick Stenning
Author-email: nick@whiteink.com
License: MIT
Keywords: sysadmin process environment
Platform: UNKNOWN
